tesseract_jax/__init__.py
tesseract_jax/_version.py
tesseract_jax/primitive.py
tesseract_jax/tesseract_compat.py
tesseract_jax-0.2.3.dist-info/licenses/LICENSE
tesseract_jax-0.2.3.dist-info/METADATA
tesseract_jax-0.2.3.dist-info/WHEEL
tesseract_jax-0.2.3.dist-info/top_level.txt
tesseract_jax-0.2.3.dist-info/RECORD
