Metadata-Version: 2.4
Name: tesseract-jax
Version: 0.2.3
Summary: Tesseract JAX executes Tesseracts as part of JAX programs, with full support for function transformations like JIT, `grad`, and more.
Author-email: "The tesseract-jax team @ Pasteur Labs" <info@simulation.science>
Project-URL: Homepage, https://github.com/pasteurlabs/tesseract-jax
Requires-Python: >=3.10
License-File: LICENSE
Requires-Dist: jax
Requires-Dist: tesseract-core
Provides-Extra: docs
Requires-Dist: sphinx; extra == "docs"
Requires-Dist: sphinx_autodoc_typehints; extra == "docs"
Requires-Dist: furo; extra == "docs"
Requires-Dist: myst-nb; extra == "docs"
Requires-Dist: sphinx_copybutton; extra == "docs"
Requires-Dist: sphinxext_opengraph; extra == "docs"
Provides-Extra: dev
Requires-Dist: pre-commit; extra == "dev"
Requires-Dist: pytest; extra == "dev"
Requires-Dist: pytest-cov; extra == "dev"
Requires-Dist: typeguard; extra == "dev"
Requires-Dist: requests; extra == "dev"
Requires-Dist: tesseract-core[runtime]; extra == "dev"
Requires-Dist: tesseract-jax[docs]; extra == "dev"
Dynamic: license-file
